thoth_vdbmanager/__init__.py
thoth_vdbmanager/initialize_vdb_plugins.py
thoth_vdbmanager/vdb_discovery.py
thoth_vdbmanager/vdb_plugin_factory.py
thoth_vdbmanager/vdbmanager/__init__.py
thoth_vdbmanager/vdbmanager/external_factory.py
thoth_vdbmanager/vdbmanager/factory.py
thoth_vdbmanager/vdbmanager/adapters/__init__.py
thoth_vdbmanager/vdbmanager/adapters/chroma_adapter.py
thoth_vdbmanager/vdbmanager/adapters/external_haystack_adapter.py
thoth_vdbmanager/vdbmanager/adapters/haystack_adapter.py
thoth_vdbmanager/vdbmanager/adapters/milvus_adapter.py
thoth_vdbmanager/vdbmanager/adapters/pgvector_adapter.py
thoth_vdbmanager/vdbmanager/adapters/qdrant_adapter.py
thoth_vdbmanager/vdbmanager/core/__init__.py
thoth_vdbmanager/vdbmanager/core/base.py
thoth_vdbmanager/vdbmanager/core/embedding_provider.py
thoth_vdbmanager/vdbmanager/core/external_embedding_manager.py
thoth_vdbmanager-0.7.2.dist-info/METADATA
thoth_vdbmanager-0.7.2.dist-info/WHEEL
thoth_vdbmanager-0.7.2.dist-info/licenses/LICENSE.md
thoth_vdbmanager-0.7.2.dist-info/RECORD
