Metadata-Version: 2.4
Name: thoth-vdbmanager
Version: 0.7.2
Summary: A vector database management module for ThothAI Project
Project-URL: Homepage, https://github.com/mptyl/thoth_vdb2
Project-URL: Bug Tracker, https://github.com/mptyl/thoth_vdb2/issues
Project-URL: Documentation, https://github.com/mptyl/thoth_vdb2#readme
Project-URL: Source Code, https://github.com/mptyl/thoth_vdb2
Author-email: Marco Pancotti <mp@tylconsulting.it>
License-File: LICENSE.md
Keywords: ai,embeddings,machine-learning,similarity-search,vector-database
Classifier: Development Status :: 4 - Beta
Classifier: Intended Audience :: Developers
Classifier: License :: OSI Approved :: MIT License
Classifier: Operating System :: OS Independent
Classifier: Programming Language :: Python :: 3
Classifier: Programming Language :: Python :: 3.12
Classifier: Topic :: Scientific/Engineering :: Artificial Intelligence
Classifier: Topic :: Software Development :: Libraries :: Python Modules
Requires-Python: >=3.13
Requires-Dist: aiohttp>=3.8.0
Requires-Dist: chroma-haystack>=3.0.0
Requires-Dist: chromadb>=1.0.0
Requires-Dist: cohere>=4.0.0
Requires-Dist: haystack-ai>=2.12.0
Requires-Dist: milvus-haystack>=0.0.16
Requires-Dist: mistralai>=0.1.0
Requires-Dist: openai>=1.0.0
Requires-Dist: pgvector-haystack>=5.0.0
Requires-Dist: pgvector>=0.4.0
Requires-Dist: psycopg>=3.0.0
Requires-Dist: pydantic>=2.0.0
Requires-Dist: pymilvus>=2.5.0
Requires-Dist: qdrant-client<1.16.0,>=1.15.0
Requires-Dist: qdrant-haystack<9.2.0,>=9.1.1
Requires-Dist: requests>=2.25.0
Requires-Dist: tenacity>=8.0.0
Requires-Dist: typing-extensions>=4.0.0
Provides-Extra: all
Requires-Dist: chroma-haystack>=3.0.0; extra == 'all'
Requires-Dist: chromadb>=1.0.0; extra == 'all'
Requires-Dist: grpcio<=1.67.1,>=1.49.1; extra == 'all'
Requires-Dist: milvus-haystack>=0.0.16; extra == 'all'
Requires-Dist: pgvector-haystack>=5.0.0; extra == 'all'
Requires-Dist: pgvector>=0.4.0; extra == 'all'
Requires-Dist: protobuf<6.0.0,>=5.26.1; extra == 'all'
Requires-Dist: psycopg>=3.0.0; extra == 'all'
Requires-Dist: pymilvus>=2.5.0; extra == 'all'
Requires-Dist: qdrant-client<1.16.0,>=1.15.0; extra == 'all'
Requires-Dist: qdrant-haystack<9.2.0,>=9.1.1; extra == 'all'
Provides-Extra: chroma
Requires-Dist: chroma-haystack>=3.0.0; extra == 'chroma'
Requires-Dist: chromadb>=1.0.0; extra == 'chroma'
Provides-Extra: dev
Requires-Dist: docker>=7.0.0; extra == 'dev'
Requires-Dist: pytest-asyncio>=0.21.0; extra == 'dev'
Requires-Dist: pytest-cov>=4.0.0; extra == 'dev'
Requires-Dist: pytest>=8.0.0; extra == 'dev'
Requires-Dist: pyyaml>=6.0.0; extra == 'dev'
Provides-Extra: milvus
Requires-Dist: grpcio<=1.67.1,>=1.49.1; extra == 'milvus'
Requires-Dist: milvus-haystack>=0.0.16; extra == 'milvus'
Requires-Dist: protobuf<6.0.0,>=5.26.1; extra == 'milvus'
Requires-Dist: pymilvus>=2.5.0; extra == 'milvus'
Provides-Extra: pgvector
Requires-Dist: pgvector-haystack>=5.0.0; extra == 'pgvector'
Requires-Dist: pgvector>=0.4.0; extra == 'pgvector'
Requires-Dist: psycopg>=3.0.0; extra == 'pgvector'
Provides-Extra: qdrant
Requires-Dist: qdrant-client<1.16.0,>=1.15.0; extra == 'qdrant'
Requires-Dist: qdrant-haystack<9.2.0,>=9.1.1; extra == 'qdrant'
Provides-Extra: test
Requires-Dist: docker>=7.0.0; extra == 'test'
Requires-Dist: pytest-asyncio>=0.21.0; extra == 'test'
Requires-Dist: pytest-cov>=4.0.0; extra == 'test'
Requires-Dist: pytest>=8.0.0; extra == 'test'
Requires-Dist: pyyaml>=6.0.0; extra == 'test'
